creasepattern/__init__.py
creasepattern/cp.py
creasepattern/cp2png.py
creasepattern/cp2svg.py
creasepattern/from_cp.py
creasepattern/from_opx.py
creasepattern/from_orh.py
creasepattern/main.py
creasepattern/opx2cp.py
creasepattern/opx2png.py
creasepattern/opx2svg.py
creasepattern/orh2cp.py
creasepattern/orh2png.py
creasepattern/orh2svg.py
creasepattern/to_cp.py
creasepattern/to_png.py
creasepattern/to_svg.py
creasepattern/util.py
creasepattern-0.0.12.dist-info/LICENSE
creasepattern-0.0.12.dist-info/METADATA
creasepattern-0.0.12.dist-info/WHEEL
creasepattern-0.0.12.dist-info/entry_points.txt
creasepattern-0.0.12.dist-info/top_level.txt
creasepattern-0.0.12.dist-info/RECORD
