Metadata-Version: 2.1
Name: creasepattern
Version: 0.0.12
Summary: Origami Crease Pattern tools
Home-page: https://github.com/qurben/creasepattern
Author: Gerben Oolbekkink
Author-email: g.j.w.oolbekkink@gmail.com
License: UNKNOWN
Project-URL: Bug Tracker, https://github.com/qurben/creasepattern/issues
Platform: UNKNOWN
Classifier: Programming Language :: Python :: 3
Classifier: License :: OSI Approved :: MIT License
Classifier: Operating System :: OS Independent
Requires-Python: >=3.6
License-File: LICENSE
Requires-Dist: Pillow
Requires-Dist: defusedxml
